Workbook

Sheet PAGOS
A1: CODIGO | B1: MOTO | C1: MODELO | E1: PLACA | F1: MOVIL | G1: PRECIO | H1: INICIAL
A2: A219782G | B2: BOXER | C2: 2026 | D2: BAJA | E2: RMC-63H | F2: 03 | G2: 6800000 | H2: 1050000
A4: COSTO -INICIAL | B4: INTERES | C4: COSTO NETO | D4: MESES | E4: MESUAL | F4: QUINCENAL | G4: SEMANAL | H4: DIARIO
A5: =G2-H2 -> 5750000 | B5: =A5*158% -> 9085000 | C5: =A5+B5 -> 14835000 | D5: 18 | E5: =C5/D5 -> 824166.67 | F5: =E5/2 -> 412083.33 | G5: =E5/4 -> 206041.67 | H5: =G5/6 -> 34340.278
A6: NOMBRES | B6: APELLIDO | C6: CEDULA | D6: NACIONALIDAD | E6: NUMERO | G6: Traspaso de propiedad | H6: DEUDA DE SEMANA
A7: DENYS JOSE | B7: GALVE QUINTERO | C7: 14747830 | D7: VENEZUELA | E7: 3017150430 | F7: SOAT | G7: FIRMA
H8: MESES
A9: SALDO ACTUAL PAGADO | C9: DEUDA A PAGAR | E9: DEUDA TOTAL. | G9: DEUDA ADQUIRIDA
A10: =I16+I26+I36+I46+I56+I66+I76+I86+I96+I106 -> 8078000 | C10: =C5-A10 -> 6757000 | E10: =C10+G10+H7 -> 6757000 | G10: =G8+F8 -> 0 | H10: =I23+I33+I43+I53+I63+I73+I83+I93+I103+I113 -> 9
A12: RENTAL MOTORS S.A.S
A15: FECHA | B15: ABONO | C15: FECHA | D15: ABONO | E15: FECHA | F15: ABONO | G15: FECHA | H15: ABONO
A16: 45894 | B16: 207000 | C16: 45901 | D16: 207000 | E16: 45908 | F16: 212000 | G16: 45915 | H16: 207000 | I16: =B22+D22+F22+H22 -> 833000
A17: 45895 | C17: 45902 | E17: 45909 | G17: 45916
A18: 45896 | C18: 45903 | E18: 45910 | G18: 45917
A19: 45897 | C19: 45904 | E19: 45911 | G19: 45918
A20: 45898 | C20: 45905 | E20: 45912 | G20: 45919
A21: 45899 | C21: 45906 | E21: 45913 | G21: 45920
B22: =SUM(B16:B21) -> 207000 | D22: =SUM(D16:D21) -> 207000 | F22: =SUM(F16:F21) -> 212000 | H22: =SUM(H16:H21) -> 207000 | I22: 1
A23: REF. | C23: REF. | E23: REF. | G23: REF. | I23: 1
A25: FECHA | B25: ABONO | C25: FECHA | D25: ABONO | E25: FECHA | F25: ABONO | G25: FECHA | H25: ABONO
A26: 45922 | B26: 207000 | C26: 45929 | D26: 207000 | E26: 45936 | F26: 207000 | G26: 45943 | H26: 207000 | I26: =B32+D32+F32+H32 -> 828000
A27: 45923 | C27: 45930 | E27: 45937 | G27: 45944
A28: 45924 | C28: 45931 | E28: 45938 | G28: 45945
A29: 45925 | C29: 45932 | E29: 45939 | G29: 45946
A30: 45926 | C30: 45933 | E30: 45940 | G30: 45947
A31: 45927 | C31: 45934 | E31: 45941 | G31: 45948
B32: =SUM(B26:B31) -> 207000 | D32: =SUM(D26:D31) -> 207000 | F32: =SUM(F26:F31) -> 207000 | H32: =SUM(H26:H31) -> 207000 | I32: 2
A33: REF. | C33: REF. | E33: REF. | G33: REF. | I33: 1
A35: FECHA | B35: ABONO | C35: FECHA | D35: ABONO | E35: FECHA | F35: ABONO | G35: FECHA | H35: ABONO
A36: 45950 | B36: 207000 | C36: 45957 | D36: 207000 | E36: 45964 | F36: 207000 | G36: 45971 | H36: 207000 | I36: =B42+D42+F42+H42 -> 828000
A37: 45951 | C37: 45958 | E37: 45965 | G37: 45972
A38: 45952 | C38: 45959 | E38: 45966 | G38: 45973
A39: 45953 | C39: 45960 | E39: 45967 | G39: 45974
A40: 45954 | C40: 45961 | E40: 45968 | G40: 45975
A41: 45955 | C41: 45962 | E41: 45969 | G41: 45976
B42: =SUM(B36:B41) -> 207000 | D42: =SUM(D36:D41) -> 207000 | F42: =SUM(F36:F41) -> 207000 | H42: =SUM(H36:H41) -> 207000 | I42: 3
A43: REF. | C43: REF. | E43: REF. | G43: REF. | I43: 1
A45: FECHA | B45: ABONO | C45: FECHA | D45: ABONO | E45: FECHA | F45: ABONO | G45: FECHA | H45: ABONO
A46: 45978 | B46: 207000 | C46: 45985 | D46: 207000 | E46: 45992 | F46: 207000 | G46: 45999 | H46: 207000 | I46: =B52+D52+F52+H52 -> 828000
A47: 45979 | C47: 45986 | E47: 45993 | G47: 46000
A48: 45980 | C48: 45987 | E48: 45994 | G48: 46001
A49: 45981 | C49: 45988 | E49: 45995 | G49: 46002
A50: 45982 | C50: 45989 | E50: 45996 | G50: 46003
A51: 45983 | C51: 45990 | E51: 45997 | G51: 46004
B52: =SUM(B46:B51) -> 207000 | D52: =SUM(D46:D51) -> 207000 | F52: =SUM(F46:F51) -> 207000 | H52: =SUM(H46:H51) -> 207000 | I52: 4
A53: REF. | C53: REF. | E53: REF. | G53: REF. | I53: 1
A55: FECHA | B55: ABONO | C55: FECHA | D55: ABONO | E55: FECHA | F55: ABONO | G55: FECHA | H55: ABONO
A56: 46006 | B56: 207000 | C56: 46013 | D56: 207000 | E56: 46020 | F56: 207000 | G56: 46027 | H56: 207000 | I56: =B62+D62+F62+H62 -> 828000
A57: 46007 | C57: 46014 | E57: 46021 | G57: 46028
A58: 46008 | C58: 46015 | E58: 46022 | G58: 46029
A59: 46009 | C59: 46016 | E59: 46023 | G59: 46030
A60: 46010 | C60: 46017 | E60: 46024 | G60: 46031
A61: 46011 | C61: 46018 | E61: 46025 | G61: 46032
B62: =SUM(B56:B61) -> 207000 | D62: =SUM(D56:D61) -> 207000 | F62: =SUM(F56:F61) -> 207000 | H62: =SUM(H56:H61) -> 207000 | I62: 5
A63: REF. | C63: REF. | E63: REF. | G63: REF. | I63: 1
A65: FECHA | B65: ABONO | C65: FECHA | D65: ABONO | E65: FECHA | F65: ABONO | G65: FECHA | H65: ABONO
A66: 46034 | B66: 207000 | C66: 46041 | D66: 207000 | E66: 46048 | F66: 207000 | G66: 46055 | H66: 207000 | I66: =B72+D72+F72+H72 -> 828000
A67: 46035 | C67: 46042 | E67: 46049 | G67: 46056
A68: 46036 | C68: 46043 | E68: 46050 | G68: 46057
A69: 46037 | C69: 46044 | E69: 46051 | G69: 46058
A70: 46038 | C70: 46045 | E70: 46052 | G70: 46059
A71: 46039 | C71: 46046 | E71: 46053 | G71: 46060
B72: =SUM(B66:B71) -> 207000 | D72: =SUM(D66:D71) -> 207000 | F72: =SUM(F66:F71) -> 207000 | H72: =SUM(H66:H71) -> 207000 | I72: 6
A73: REF. | B73: M05284498 | C73: REF. | E73: REF. | F73: M020863 | G73: REF. | H73: M09626676 | I73: 1
A75: FECHA | B75: ABONO | C75: FECHA | D75: ABONO | E75: FECHA | F75: ABONO | G75: FECHA | H75: ABONO
A76: 46062 | B76: 207000 | C76: 46069 | D76: 207000 | E76: 46076 | F76: 207000 | G76: 46083 | H76: 207000 | I76: =B82+D82+F82+H82 -> 828000
A77: 46063 | C77: 46070 | E77: 46077 | G77: 46084
A78: 46064 | C78: 46071 | E78: 46078 | G78: 46085
A79: 46065 | C79: 46072 | E79: 46079 | G79: 46086
A80: 46066 | C80: 46073 | E80: 46080 | G80: 46087
A81: 46067 | C81: 46074 | E81: 46081 | G81: 46088
B82: =SUM(B76:B81) -> 207000 | D82: =SUM(D76:D81) -> 207000 | F82: =SUM(F76:F81) -> 207000 | H82: =SUM(H76:H81) -> 207000 | I82: 7
A83: REF. | B83: M01160032 | C83: REF. | D83: M16748276 | E83: REF. | G83: REF. | I83: 1
A85: FECHA | B85: ABONO | C85: FECHA | D85: ABONO | E85: FECHA | F85: ABONO | G85: FECHA | H85: ABONO
A86: 46090 | B86: 207000 | C86: 46097 | D86: 207000 | E86: 46104 | F86: 207000 | G86: 46111 | H86: 207000 | I86: =B92+D92+F92+H92 -> 828000
A87: 46091 | C87: 46098 | E87: 46105 | G87: 46112
A88: 46092 | C88: 46099 | E88: 46106 | G88: 46113
A89: 46093 | C89: 46100 | E89: 46107 | G89: 46114
A90: 46094 | C90: 46101 | E90: 46108 | G90: 46115
A91: 46095 | C91: 46102 | E91: 46109 | G91: 46116
B92: =SUM(B86:B91) -> 207000 | D92: =SUM(D86:D91) -> 207000 | F92: =SUM(F86:F91) -> 207000 | H92: =SUM(H86:H91) -> 207000 | I92: 8
A93: REF. | C93: REF. | E93: REF. | G93: REF. | I93: 1
A95: FECHA | B95: ABONO | C95: FECHA | D95: ABONO | E95: FECHA | F95: ABONO | G95: FECHA | H95: ABONO
A96: 46118 | B96: 207000 | C96: 46125 | D96: 207000 | E96: 46132 | F96: 207000 | G96: 46139 | H96: 207000 | I96: =B102+D102+F102+H102 -> 828000
A97: 46119 | C97: 46126 | E97: 46133 | G97: 46140
A98: 46120 | C98: 46127 | E98: 46134 | G98: 46141
A99: 46121 | C99: 46128 | E99: 46135 | G99: 46142
A100: 46122 | C100: 46129 | E100: 46136 | G100: 46143
A101: 46123 | C101: 46130 | E101: 46137 | G101: 46144
B102: =SUM(B96:B101) -> 207000 | D102: =SUM(D96:D101) -> 207000 | F102: =SUM(F96:F101) -> 207000 | H102: =SUM(H96:H101) -> 207000 | I102: 9
A103: REF. | C103: REF. | E103: REF. | G103: REF. | I103: 1
A105: FECHA | B105: ABONO | C105: FECHA | D105: ABONO | E105: FECHA | F105: ABONO | G105: FECHA | H105: ABONO
A106: 46146 | B106: 207000 | C106: 46153 | D106: 207000 | E106: 46160 | F106: 207000 | G106: 46167 | I106: =B112+D112+F112+H112 -> 621000
A107: 46147 | C107: 46154 | E107: 46161 | G107: 46168
A108: 46148 | C108: 46155 | E108: 46162 | G108: 46169
A109: 46149 | C109: 46156 | E109: 46163 | G109: 46170
A110: 46150 | C110: 46157 | E110: 46164 | G110: 46171
A111: 46151 | C111: 46158 | E111: 46165 | G111: 46172
B112: =SUM(B106:B111) -> 207000 | D112: =SUM(D106:D111) -> 207000 | F112: =SUM(F106:F111) -> 207000 | H112: =SUM(H106:H111) -> 0 | I112: 10
A113: REF. | C113: REF. | E113: REF. | G113: REF.

Sheet SEMANAL
A1: RENTAL MOTORS S.A.S
A3: SOLO PAGOS POR BANCOLOMBIA | C3: =PAGOS!A7 -> DENYS JOSE
A4: FECHA DEL PRESTAMOS | B4: =PAGOS!A16 -> 45894
A5: COSTO DEL VEICULO | B5: =PAGOS!G2 -> 6800000 | C5: MOVIL 03
A6: INICIAL DEL VEICULO | B6: =PAGOS!H2 -> 1050000
A7: PRESTAMO | B7: =B5-B6 -> 5750000
A8: TASA DE INTERES ( 1,9%) | B8: =PAGOS!C5 -> 14835000
A9: COSTO NETO DE LA MOTO
A10: SOAT | B10: =PAGOS!F8 | C10: =PAGOS!G4 -> SEMANAL
A12: Traspaso de propiedad | B12: =PAGOS!G8
A13: MENSUALIDA GPS | C13: =PAGOS!G5 -> 206041.67
A14: TOTAL APAGAR GPS
A15: MESES A PAGAR | B15: 26
A16: COSTO NETO DE LA MOTO CON LOS TRAMITES Y SERVICIO | B16: =B9+B10+B11+B12+B14 -> 0
A17: SALDO PAGADO | B17: SALDO PENDIENTE | C17: DEUDA ADQUIRIDA | D17: MESES ADQUIRIDO | E17: MESES PAGADO
A18: =PAGOS!A10 -> 8078000 | B18: =PAGOS!C10 -> 6757000 | C18: =PAGOS!G10 -> 0
