Workbook

Sheet PAGOS
B1: MOTO | C1: MODELO | D1: MARCA | E1: PLACA | F1: MOVIL | G1: PRECIO | H1: INICIAL
A2: A21987G | B2: SBR | C2: 2026 | D2: BERA | E2: YIE71H | F2: MOVIL 08 | G2: 6000000 | H2: 800000
A4: COSTO -INICIAL | B4: INTERES | C4: COSTO NETO | D4: MESES | E4: MESUAL | F4: QUINCENAL | G4: SEMANAL | H4: DIARIO
A5: =G2-H2 -> 5200000 | B5: =2.3 -> 2.3 | C5: 13600000 | D5: 18 | E5: =C5/D5 -> 755555.56 | F5: =E5/2 -> 377777.78 | G5: =F5/2 -> 188888.89 | H5: =G5/6 -> 31481.481
A6: NOMBRES | B6: APELLIDO | C6: CEDULA | D6: NACIONALIDAD | E6: NUMERO | G6: Traspaso de propiedad | H6: DEUDA DE SEMANA
A7: JESUS ANDRES | B7: LOPEZ MORALES | C7: 30082499 | D7: VENEZOLANA | E7: 3169408429 | F7: SOAT | G7: FIRMA
H8: MESES
A9: SALDO ACTUAL PAGADO | C9: DEUDA A PAGAR | E9: DEUDA TOTAL. | G9: DEUDA ADQUIRIDA
A10: =I16+I26+I36+I46+I56+I66+I76+I86+I95 -> 3971000 | C10: =C5-A10 -> 9629000 | E10: =C10+G10 -> 9629000 | H10: =I23+I33+I43+I53+I63+I73+I83 -> 5
A12: RENTAL MOTORS S.A.S
A15: FECHA | B15: ABONO | C15: FECHA | D15: ABONO | E15: FECHA | F15: ABONO | G15: FECHA | H15: ABONO
A16: 46020 | C16: 46027 | E16: 46034 | G16: 46041 | I16: =B22+D22+F22+H22 -> 756000
A17: 46021 | C17: 46028 | E17: 46035 | G17: 46042
A18: 46022 | B18: 189000 | C18: 46029 | D18: 189000 | E18: 46036 | F18: 189000 | G18: 46043 | H18: 189000
A19: 46023 | C19: 46030 | E19: 46037 | G19: 46044
A20: 46024 | C20: 46031 | E20: 46038 | G20: 46045
A21: 46025 | C21: 46032 | E21: 46039 | G21: 46046
B22: =SUM(B16:B21) -> 189000 | D22: =SUM(D16:D21) -> 189000 | F22: =SUM(F16:F21) -> 189000 | H22: =SUM(H16:H21) -> 189000 | I22: 1
A23: REF. | C23: REF. | E23: REF. | G23: REF. | I23: 1
A25: FECHA | B25: ABONO | C25: FECHA | D25: ABONO | E25: FECHA | F25: ABONO | G25: FECHA | H25: ABONO
A26: 46048 | C26: 46055 | D26: 189000 | E26: 46062 | F26: 189000 | G26: 46069 | H26: 189000 | I26: =B32+D32+F32+H32 -> 756000
A27: 46049 | C27: 46056 | E27: 46063 | G27: 46070
A28: 46050 | B28: 189000 | C28: 46057 | E28: 46064 | G28: 46071
A29: 46051 | C29: 46058 | E29: 46065 | G29: 46072
A30: 46052 | C30: 46059 | E30: 46066 | G30: 46073
A31: 46053 | C31: 46060 | E31: 46067 | G31: 46074
B32: =SUM(B26:B31) -> 189000 | D32: =SUM(D26:D31) -> 189000 | F32: =SUM(F26:F31) -> 189000 | H32: =SUM(H26:H31) -> 189000 | I32: 2
A33: REF. | C33: REF. | D33: M02140271 | E33: REF. | F33: M00156218 | G33: REF. | H33: M03166817 | I33: 1
A35: FECHA | B35: ABONO | C35: FECHA | D35: ABONO | E35: FECHA | F35: ABONO | G35: FECHA | H35: ABONO
A36: 46076 | B36: 189000 | C36: 46083 | D36: 189000 | E36: 46090 | F36: 189000 | G36: 46097 | H36: 189000 | I36: =B42+D42+F42+H42 -> 756000
A37: 46077 | C37: 46084 | E37: 46091 | G37: 46098
A38: 46078 | C38: 46085 | E38: 46092 | G38: 46099
A39: 46079 | C39: 46086 | E39: 46093 | G39: 46100
A40: 46080 | C40: 46087 | E40: 46094 | G40: 46101
A41: 46081 | C41: 46088 | E41: 46095 | G41: 46102
B42: =SUM(B36:B41) -> 189000 | D42: =SUM(D36:D41) -> 189000 | F42: =SUM(F36:F41) -> 189000 | H42: =SUM(H36:H41) -> 189000 | I42: 3
A43: REF. | C43: REF. | E43: REF. | G43: REF. | I43: 1
A45: FECHA | B45: ABONO | C45: FECHA | D45: ABONO | E45: FECHA | F45: ABONO | G45: FECHA | H45: ABONO
A46: 46104 | B46: 189000 | C46: 46111 | D46: 189000 | E46: 46118 | F46: 189000 | G46: 46125 | H46: 189000 | I46: =B52+D52+F52+H52 -> 756000
A47: 46105 | C47: 46112 | E47: 46119 | G47: 46126
A48: 46106 | C48: 46113 | E48: 46120 | G48: 46127
A49: 46107 | C49: 46114 | E49: 46121 | G49: 46128
A50: 46108 | C50: 46115 | E50: 46122 | G50: 46129
A51: 46109 | C51: 46116 | E51: 46123 | G51: 46130
B52: =SUM(B46:B51) -> 189000 | D52: =SUM(D46:D51) -> 189000 | F52: =SUM(F46:F51) -> 189000 | H52: =SUM(H46:H51) -> 189000 | I52: 4
A53: REF. | C53: REF. | E53: REF. | G53: REF. | I53: 1
A55: FECHA | B55: ABONO | C55: FECHA | D55: ABONO | E55: FECHA | F55: ABONO | G55: FECHA | H55: ABONO
A56: 46132 | B56: 189000 | C56: 46139 | D56: 189000 | E56: 46146 | F56: 189000 | G56: 46153 | H56: 190000 | I56: =B62+D62+F62+H62 -> 757000
A57: 46133 | C57: 46140 | E57: 46147 | G57: 46154
A58: 46134 | C58: 46141 | E58: 46148 | G58: 46155
A59: 46135 | C59: 46142 | E59: 46149 | G59: 46156
A60: 46136 | C60: 46143 | E60: 46150 | G60: 46157
A61: 46137 | C61: 46144 | E61: 46151 | G61: 46158
B62: =SUM(B56:B61) -> 189000 | D62: =SUM(D56:D61) -> 189000 | F62: =SUM(F56:F61) -> 189000 | H62: =SUM(H56:H61) -> 190000 | I62: 5
A63: REF. | C63: REF. | E63: REF. | G63: REF. | I63: 1
A65: FECHA | B65: ABONO | C65: FECHA | D65: ABONO | E65: FECHA | F65: ABONO | G65: FECHA | H65: ABONO
A66: 46160 | B66: 190000 | C66: 46167 | E66: 46174 | G66: 46181 | I66: =B72+D72+F72+H72 -> 190000
A67: 46161 | C67: 46168 | E67: 46175 | G67: 46182
A68: 46162 | C68: 46169 | E68: 46176 | G68: 46183
A69: 46163 | C69: 46170 | E69: 46177 | G69: 46184
A70: 46164 | C70: 46171 | E70: 46178 | G70: 46185
A71: 46165 | C71: 46172 | E71: 46179 | G71: 46186
B72: =SUM(B66:B71) -> 190000 | D72: =SUM(D66:D71) -> 0 | F72: =SUM(F66:F71) -> 0 | H72: =SUM(H66:H71) -> 0 | I72: 6
A73: REF. | B73: M05284498 | C73: REF. | E73: REF. | G73: REF.
A75: FECHA | B75: ABONO | C75: FECHA | D75: ABONO | E75: FECHA | F75: ABONO | G75: FECHA | H75: ABONO
I76: =B82+D82+F82+H82 -> 0
B82: =SUM(B76:B81) -> 0 | D82: =SUM(D76:D81) -> 0 | F82: =SUM(F76:F81) -> 0 | H82: =SUM(H76:H81) -> 0 | I82: 7
A83: REF. | C83: REF. | E83: REF. | G83: REF.
A85: FECHA | B85: ABONO | C85: FECHA | D85: ABONO | E85: FECHA | F85: ABONO | G85: FECHA | H85: ABONO
I86: =B92+D92+F92+H92 -> 0
B92: =SUM(B86:B91) -> 0 | D92: =SUM(D86:D91) -> 0 | F92: =SUM(F86:F91) -> 0 | H92: =SUM(H86:H91) -> 0 | I92: 8
A94: FECHA | B94: ABONO | C94: FECHA | D94: ABONO | E94: FECHA | F94: ABONO | G94: FECHA | H94: ABONO
I95: =B101+D101+F101+H101 -> 0
B101: =SUM(B95:B100) -> 0 | D101: =SUM(D95:D100) -> 0 | F101: =SUM(F95:F100) -> 0 | H101: =SUM(H95:H100) -> 0 | I101: 9

Sheet Hoja 2
A1: RENTAL MOTORS S.A.S
A3: SOLO PAGOS POR BANCOLOMBIA | C3: =PAGOS!A7 -> JESUS ANDRES
A4: FECHA DEL PRESTAMOS | B4: =PAGOS!A16 -> 46020
A5: COSTO DEL VEICULO | B5: =PAGOS!G2 -> 6000000 | C5: MOVIL 08
A6: INICIAL DEL VEICULO | B6: =PAGOS!H2 -> 800000
A7: PRESTAMO | B7: =PAGOS!A5 -> 5200000
A8: TASA DE INTERES ( 2,38) | B8: =PAGOS!C5 -> 13600000
A9: COSTO NETO DE LA MOTO | B9: =PAGOS!C5 -> 13600000
A10: SOAT | B10: 380000
A12: Traspaso de propiedad | B12: 280000
A13: MENSUALIDA GPS | B13: 25000
A14: TOTAL APAGAR GPS
A15: MESES A PAGAR | B15: 26
A16: COSTO NETO DE LA MOTO CON LOS TRAMITES Y SERVICIO
A17: SALDO PAGADO | B17: SALDO PENDIENTE | C17: DEUDA ADQUIRIDA | D17: MESES ADQUIRIDO | E17: MESES PAGADO
A18: =PAGOS!A10 -> 3971000 | B18: =PAGOS!C10 -> 9629000 | C18: =PAGOS!E10 -> 9629000
