Workbook

Sheet PAGOS
A1: CODIGO | B1: MOTO | C1: MODELO | D1: MARCA | E1: PLACA | F1: MOVIL | G1: PRECIO | H1: INICIAL | I1: 12699500
A2: A2175 | B2: SBR | C2: 2024 | D2: BERA | E2: NDE68H- | F2: 32 | G2: 5600000 | H2: 450000
A4: COSTO -INICIAL | B4: INTERES | C4: COSTO NETO | D4: MESES | E4: MESUAL | F4: QUINCENAL | G4: SEMANAL | H4: DIARIO
A5: =G2-H2 -> 5150000 | B5: =A5*1.41 -> 7261500 | C5: =B5+A5 -> 12411500 | D5: 18 | E5: 714000 | F5: =E5/2 -> 357000 | G5: =F5/2 -> 178500 | H5: =G5/6 -> 29750
A6: NOMBRES | B6: APELLIDO | C6: P.P.T | D6: NACIONALIDAD | E6: NUMERO | F6: SOAT | G6: Traspaso de propiedad | H6: PRESTAMO.
A7: JULIO CESAR | B7: HERNANDEZ | C7: 5882282 | D7: VENEZOLANO | F7: ACTIVO | G7: ACTIVO | H7: 0
A9: SALDO ACTUAL PAGADO | C9: DEUDA A PAGAR | E9: DEUDA TOTAL | G9: D. ADQUIRIDA | H9: CUOTA MENSUAL #
A10: =I15+I25+I35+I45+I55+I65+I75+I85+I95+I105+I115+I125+I135+I145+I155 -> 10530000 | C10: =C5-A10 -> 1881500 | E10: =C10+G10 -> 1881500
H11: =I22+I32+I42+I52+I62+I72+I82+I92+I102+I112+I122+I132+I142+I152+I162 -> 14
A12: RENTAL MOTORS S.A.S
A14: FECHA | B14: ABONO | C14: FECHA | D14: ABONO | E14: FECHA | F14: ABONO | G14: FECHA | H14: ABONO
C15: 45761 | E15: 45768 | G15: 45775 | I15: =B21+D21+F21+H21 -> 630000
C16: 45762 | E16: 45769 | G16: 45776
C17: 45763 | D17: 180000 | E17: 45770 | F17: 180000 | G17: 45777 | H17: 180000
C18: 45764 | E18: 45771 | G18: 45778
A19: 45758 | B19: 90000 | C19: 45765 | E19: 45772 | G19: 45779
A20: 45759 | C20: 45766 | E20: 45773 | G20: 45780
B21: =SUM(B15:B20) -> 90000 | D21: =SUM(D15:D20) -> 180000 | F21: =SUM(F15:F20) -> 180000 | H21: =SUM(H15:H20) -> 180000 | I21: 1
A22: REF. | B22: EFECTIIVO | C22: REF. | D22: M5031425 | E22: REF. | F22: M5922059 | G22: REF. | H22: M10904490 | I22: 1
A24: FECHA | B24: ABONO | C24: FECHA | D24: ABONO | E24: FECHA | F24: ABONO | G24: FECHA | H24: ABONO
A25: 45782 | C25: 45789 | E25: 45796 | G25: 45803 | I25: =B31+D31+F31+H31 -> 720000
A26: 45783 | C26: 45790 | E26: 45797 | G26: 45804
A27: 45784 | B27: 180000 | C27: 45791 | D27: 180000 | E27: 45798 | F27: 180000 | G27: 45805 | H27: 180000
A28: 45785 | C28: 45792 | E28: 45799 | G28: 45806
A29: 45786 | C29: 45793 | E29: 45800 | G29: 45807
A30: 45787 | C30: 45794 | E30: 45801 | G30: 45808
B31: =SUM(B25:B30) -> 180000 | D31: =SUM(D25:D30) -> 180000 | F31: =SUM(F25:F30) -> 180000 | H31: =SUM(H25:H30) -> 180000 | I31: 2
A32: REF. | B32: M10288520 | C32: REF. | D32: M14985720 | E32: REF. | F32: EFECTIVO | G32: REF. | H32: M4937797 | I32: 1
A34: FECHA | B34: ABONO | C34: FECHA | D34: ABONO | E34: FECHA | F34: ABONO | G34: FECHA | H34: ABONO
A35: 45810 | C35: 45817 | E35: 45824 | G35: 45831 | I35: =B41+D41+F41+H41 -> 720000
A36: 45811 | C36: 45818 | E36: 45825 | G36: 45832
A37: 45812 | C37: 45819 | E37: 45826 | G37: 45833
A38: 45813 | B38: 180000 | C38: 45820 | D38: 180000 | E38: 45827 | F38: 180000 | G38: 45834 | H38: 180000
A39: 45814 | C39: 45821 | E39: 45828 | G39: 45835
A40: 45815 | C40: 45822 | E40: 45829 | G40: 45836
B41: =SUM(B35:B40) -> 180000 | D41: =SUM(D35:D40) -> 180000 | F41: =SUM(F35:F40) -> 180000 | H41: =SUM(H35:H40) -> 180000 | I41: 3
A42: REF. | B42: M10720724 | C42: REF. | D42: EFECTIVO | E42: REF. | F42: M14573142 | G42: REF. | I42: 1
A44: FECHA | B44: ABONO | C44: FECHA | D44: ABONO | E44: FECHA | F44: ABONO | G44: FECHA | H44: ABONO
A45: 45838 | C45: 45845 | E45: 45852 | G45: 45859 | I45: =B51+D51+F51+H51 -> 720000
A46: 45839 | C46: 45846 | E46: 45853 | G46: 45860
A47: 45840 | C47: 45847 | E47: 45854 | G47: 45861
A48: 45841 | B48: 180000 | C48: 45848 | D48: 180000 | E48: 45855 | F48: 180000 | G48: 45862 | H48: 180000
A49: 45842 | C49: 45849 | E49: 45856 | G49: 45863
A50: 45843 | C50: 45850 | E50: 45857 | G50: 45864
B51: =SUM(B45:B50) -> 180000 | D51: =SUM(D45:D50) -> 180000 | F51: =SUM(F45:F50) -> 180000 | H51: =SUM(H45:H50) -> 180000 | I51: 4
A52: REF. | C52: REF. | E52: REF. | F52: efectivo | G52: REF. | H52: M14573142 | I52: 1
A54: FECHA | B54: ABONO | C54: FECHA | D54: ABONO | E54: FECHA | F54: ABONO | G54: FECHA | H54: ABONO
A55: 45866 | C55: 45873 | E55: 45880 | G55: 45887 | I55: =B61+D61+F61+H61 -> 720000
A56: 45867 | C56: 45874 | E56: 45881 | G56: 45888
A57: 45868 | C57: 45875 | E57: 45882 | G57: 45889
A58: 45869 | B58: 180000 | C58: 45876 | D58: 180000 | E58: 45883 | F58: 180000 | G58: 45890 | H58: 180000
A59: 45870 | C59: 45877 | E59: 45884 | G59: 45891
A60: 45871 | C60: 45878 | E60: 45885 | G60: 45892
B61: =SUM(B55:B60) -> 180000 | D61: =SUM(D55:D60) -> 180000 | F61: =SUM(F55:F60) -> 180000 | H61: =SUM(H55:H60) -> 180000 | I61: 5
A62: REF. | B62: m1370896 | C62: REF. | D62: david plata | E62: REF. | F62: david plata | G62: REF. | H62: david plata | I62: 1
A64: FECHA | B64: ABONO | C64: FECHA | D64: ABONO | E64: FECHA | F64: ABONO | G64: FECHA | H64: ABONO
A65: 45894 | C65: 45901 | E65: 45908 | G65: 45915 | I65: =B71+D71+F71+H71 -> 720000
A66: 45895 | C66: 45902 | E66: 45909 | G66: 45916
A67: 45896 | C67: 45903 | E67: 45910 | G67: 45917
A68: 45897 | B68: 180000 | C68: 45904 | D68: 180000 | E68: 45911 | F68: 180000 | G68: 45918 | H68: 180000
A69: 45898 | C69: 45905 | E69: 45912 | G69: 45919
A70: 45899 | C70: 45906 | E70: 45913 | G70: 45920
B71: =SUM(B65:B70) -> 180000 | D71: =SUM(D65:D70) -> 180000 | F71: =SUM(F65:F70) -> 180000 | H71: =SUM(H65:H70) -> 180000 | I71: 6
A72: REF. | C72: REF. | E72: REF. | G72: REF. | I72: 1
A74: FECHA | B74: ABONO | C74: FECHA | D74: ABONO | E74: FECHA | F74: ABONO | G74: FECHA | H74: ABONO
A75: 45922 | C75: 45929 | E75: 45936 | G75: 45943 | I75: =B81+D81+F81+H81 -> 720000
A76: 45923 | C76: 45930 | E76: 45937 | G76: 45944
A77: 45924 | C77: 45931 | E77: 45938 | G77: 45945
A78: 45925 | B78: 180000 | C78: 45932 | D78: 180000 | E78: 45939 | F78: 180000 | G78: 45946 | H78: 180000
A79: 45926 | C79: 45933 | E79: 45940 | G79: 45947
A80: 45927 | C80: 45934 | E80: 45941 | G80: 45948
B81: =SUM(B75:B80) -> 180000 | D81: =SUM(D75:D80) -> 180000 | F81: =SUM(F75:F80) -> 180000 | H81: =SUM(H75:H80) -> 180000 | I81: 7
A82: REF. | C82: REF. | E82: REF. | G82: REF. | I82: 1
A84: FECHA | B84: ABONO | C84: FECHA | D84: ABONO | E84: FECHA | F84: ABONO | G84: FECHA | H84: ABONO
A85: 45950 | C85: 45957 | E85: 45964 | G85: 45971 | I85: =B91+D91+F91+H91 -> 720000
A86: 45951 | C86: 45958 | E86: 45965 | G86: 45972
A87: 45952 | C87: 45959 | E87: 45966 | G87: 45973
A88: 45953 | B88: 180000 | C88: 45960 | D88: 180000 | E88: 45967 | F88: 180000 | G88: 45974 | H88: 180000
A89: 45954 | C89: 45961 | E89: 45968 | G89: 45975
A90: 45955 | C90: 45962 | E90: 45969 | G90: 45976
B91: =SUM(B85:B90) -> 180000 | D91: =SUM(D85:D90) -> 180000 | F91: =SUM(F85:F90) -> 180000 | H91: =SUM(H85:H90) -> 180000 | I91: 8
A92: REF. | C92: REF. | E92: REF. | G92: REF. | I92: 1
A94: FECHA | B94: ABONO | C94: FECHA | D94: ABONO | E94: FECHA | F94: ABONO | G94: FECHA | H94: ABONO
A95: 45978 | C95: 45985 | E95: 45992 | G95: 45999 | I95: =B101+D101+F101+H101 -> 720000
A96: 45979 | C96: 45986 | E96: 45993 | G96: 46000
A97: 45980 | C97: 45987 | E97: 45994 | G97: 46001
A98: 45981 | B98: 180000 | C98: 45988 | D98: 180000 | E98: 45995 | F98: 180000 | G98: 46002 | H98: 180000
A99: 45982 | C99: 45989 | E99: 45996 | G99: 46003
A100: 45983 | C100: 45990 | E100: 45997 | G100: 46004
B101: =SUM(B95:B100) -> 180000 | D101: =SUM(D95:D100) -> 180000 | F101: =SUM(F95:F100) -> 180000 | H101: =SUM(H95:H100) -> 180000 | I101: 9
A102: REF. | C102: REF. | E102: REF. | G102: REF. | I102: 1
A104: FECHA | B104: ABONO | C104: FECHA | D104: ABONO | E104: FECHA | F104: ABONO | G104: FECHA | H104: ABONO
A105: 46006 | C105: 46013 | E105: 46020 | G105: 46027 | I105: =B111+D111+F111+H111 -> 720000
A106: 46007 | C106: 46014 | E106: 46021 | G106: 46028
A107: 46008 | C107: 46015 | D107: 162000 | E107: 46022 | G107: 46029
A108: 46009 | B108: 180000 | C108: 46016 | D108: 18000 | E108: 46023 | F108: 180000 | G108: 46030 | H108: 180000
A109: 46010 | C109: 46017 | E109: 46024 | G109: 46031
A110: 46011 | C110: 46018 | E110: 46025 | G110: 46032
B111: =SUM(B105:B110) -> 180000 | D111: =SUM(D105:D110) -> 180000 | F111: =SUM(F105:F110) -> 180000 | H111: =SUM(H105:H110) -> 180000 | I111: 10
A112: REF. | C112: REF. | E112: REF. | F112: M13572352 | G112: REF. | H112: M0981080 | I112: 1
...

Sheet MOVIL 32
A1: RENTAL MOTORS S.A.S Nit. 901843215-2
A5: FOTO | C5: =DATA!B4 -> NOMBRE Y APELLIDO | D5: =DATA!C4 -> CEDULA | E5: =DATA!D4 -> N/CONTACTO
C6: =DATA!B5 -> JULIO CESAR | D6: =PAGOS!C7 -> 5882282 | E6: =DATA!D5 -> 3126889237
C7: =PAGOS!A7 -> JULIO CESAR | D7: MOVIL 32
C9: =PAGOS!A9 -> SALDO ACTUAL PAGADO | D9: =PAGOS!C9 -> DEUDA A PAGAR
C12: =PAGOS!A10 -> 10530000 | D12: =PAGOS!C10 -> 1881500
A13: CUOTAS TOTALES | C13: =PAGOS!H9 -> CUOTA MENSUAL # | D13: CUOTAS RESTANTES
A14: =PAGOS!D5 -> 18 | C14: =PAGOS!H11 -> 14 | D14: =PAGOS!D5-PAGOS!H11 -> 4
A15: CODIGO | B15: MOTO | C15: MODELO | D15: MARCA | E15: PLACA
A16: A2175 | B16: =PAGOS!B2 -> SBR | C16: =PAGOS!C2 -> 2024 | D16: =PAGOS!D2 -> BERA | E16: RLI49H
C17: SOAT | D17: Traspaso de propiedad | E17: PRESTAMO.
C18: ACTIVO | D18: ACTIVO | E18: 0

Sheet DATA
A1: RENTAL MOTORS S.A.S Nit. 901843215-2
A4: MOVIL | B4: NOMBRE Y APELLIDO | C4: CEDULA | D4: N/CONTACTO | E4: CORREO ELECTRONICO | F4: FECHA DE INICIO | G4: DIRECCION | H4: CIUDAD | I4: BARRIO
A5: MOVIL 31 | B5: =PAGOS!A7 -> JULIO CESAR | C5: =PAGOS!C7 -> 5882282 | D5: 3126889237 | F5: 45758
B8: DATOS PERSONALES
B9: NOMBRE Y APELLIDO | C9: PARESTESCO | D9: CEDULA | E9: N/CONTACTO
B13: NOMBRE Y APELLIDO | C13: PARESTESCO | D13: CEDULA | E13: N/CONTACTO
