Workbook

Sheet PAGOS
A1: CODIGO | B1: MOTO | C1: MODELO | D1: MARCA | E1: PLACA | F1: MOVIL | G1: PRECIO | H1: INICIAL
A2: A219782G | B2: BERA | C2: 2025 | D2: SBR150 | E2: UGO53H | F2: 39 | G2: 5800000 | H2: 800000
A4: COSTO -INICIAL | B4: INTERES | C4: COSTO NETO | D4: MESES | E4: MESUAL | F4: QUINCENAL | G4: SEMANAL | H4: DIARIO
A5: =G2 -> 5800000 | B5: =A5*1.3 -> 7540000 | C5: =B5+A5 -> 13340000 | D5: 18 | E5: =C5/D5 -> 741111.11 | F5: =E5/2 -> 370555.56 | G5: =F5/2 -> 185277.78 | H5: =G5/6 -> 30879.63
A6: NOMBRES | B6: APELLIDO | C6: CEDULA | D6: NACIONALIDAD | E6: NUMERO | F6: SOAT | G6: Traspaso de propiedad | H6: PRESTAMO.
A7: ERIK FERNANDO | B7: SALAZAR | C7: PPT -5383521 | D7: VENEZOLANO | E7: 3014696455 | F7: ACTIVO | G7: ACTIVO | H7: 0
F8: 380000 | G8: 280000
A9: SALDO ACTUAL PAGADO | C9: DEUDA A PAGAR | E9: DEUDA TOTAL | G9: D. ADQUIRIDA | H9: MESES
A10: =I15+I25+I35+I45+I55+I65+I75+I85 -> 4978225 | C10: =C5-A10 -> 8361775 | E10: =C10+G10 -> 8361775
H11: =I22+I32+I42+I52+I62+I72+I82+I92 -> 7
A12: RENTAL MOTORS S.A.S
A14: FECHA | B14: ABONO | C14: FECHA | D14: ABONO | E14: FECHA | F14: ABONO | G14: FECHA | H14: ABONO
A15: 45971 | B15: 154225 | C15: 45978 | D15: 185000 | E15: 45985 | F15: 185000 | G15: 45992 | H15: 110000 | I15: =B21+D21+F21+H21 -> 634225
A16: 45972 | C16: 45979 | E16: 45986 | G16: 45993
A17: 45973 | C17: 45980 | E17: 45987 | G17: 45994
A18: 45974 | C18: 45981 | E18: 45988 | G18: 45995
A19: 45975 | C19: 45982 | E19: 45989 | G19: 45996
A20: 45976 | C20: 45983 | E20: 45990 | G20: 45997
B21: =SUM(B15:B20) -> 154225 | D21: =SUM(D15:D20) -> 185000 | F21: =SUM(F15:F20) -> 185000 | H21: =SUM(H15:H20) -> 110000 | I21: 1
A22: REF. | B22: M02629925 | C22: REF. | D22: M16437684 | E22: REF. | F22: M05720987 | G22: REF. | I22: 1
A24: FECHA | B24: ABONO | C24: FECHA | D24: ABONO | E24: FECHA | F24: ABONO | G24: FECHA | H24: ABONO
A25: 45999 | B25: 153000 | C25: 46006 | D25: 185000 | E25: 46013 | F25: 185000 | G25: 46020 | H25: 120000 | I25: =B31+D31+F31+H31 -> 675000
A26: 46000 | B26: 32000 | C26: 46007 | E26: 46014 | G26: 46021
A27: 46001 | C27: 46008 | E27: 46015 | G27: 46022
A28: 46002 | C28: 46009 | E28: 46016 | G28: 46023
A29: 46003 | C29: 46010 | E29: 46017 | G29: 46024
A30: 46004 | C30: 46011 | E30: 46018 | G30: 46025
B31: =SUM(B25:B30) -> 185000 | D31: =SUM(D25:D30) -> 185000 | F31: =SUM(F25:F30) -> 185000 | H31: =SUM(H25:H30) -> 120000 | I31: 2
A32: REF. | B32: 35618 | C32: REF. | D32: M1061742 | E32: REF. | F32: M12039071 | G32: REF. | H32: M18963662 | I32: 1
A34: FECHA | B34: ABONO | C34: FECHA | D34: ABONO | E34: FECHA | F34: ABONO | G34: FECHA | H34: ABONO
A35: 46027 | B35: 170000 | C35: 46034 | D35: 185000 | E35: 46041 | F35: 185000 | G35: 46048 | H35: 185000 | I35: =B41+D41+F41+H41 -> 740000
A36: 46028 | B36: 15000 | C36: 46035 | E36: 46042 | G36: 46049
A37: 46029 | C37: 46036 | E37: 46043 | G37: 46050
A38: 46030 | C38: 46037 | E38: 46044 | G38: 46051
A39: 46031 | C39: 46038 | E39: 46045 | G39: 46052
A40: 46032 | C40: 46039 | E40: 46046 | G40: 46053
B41: =SUM(B35:B40) -> 185000 | D41: =SUM(D35:D40) -> 185000 | F41: =SUM(F35:F40) -> 185000 | H41: =SUM(H35:H40) -> 185000 | I41: 3
A42: REF. | B42: M12690057 | C42: REF. | D42: M13930326 | E42: REF. | G42: REF. | I42: 1
A44: FECHA | B44: ABONO | C44: FECHA | D44: ABONO | E44: FECHA | F44: ABONO | G44: FECHA | H44: ABONO
A45: 46055 | B45: 185000 | C45: 46062 | D45: 185000 | E45: 46069 | F45: 185000 | G45: 46076 | H45: 185000 | I45: =B51+D51+F51+H51 -> 740000
A46: 46056 | C46: 46063 | E46: 46070 | G46: 46077
A47: 46057 | C47: 46064 | E47: 46071 | G47: 46078
A48: 46058 | C48: 46065 | E48: 46072 | G48: 46079
A49: 46059 | C49: 46066 | E49: 46073 | G49: 46080
A50: 46060 | C50: 46067 | E50: 46074 | G50: 46081
B51: =SUM(B45:B50) -> 185000 | D51: =SUM(D45:D50) -> 185000 | F51: =SUM(F45:F50) -> 185000 | H51: =SUM(H45:H50) -> 185000 | I51: 4
A52: REF. | C52: REF. | E52: REF. | G52: REF. | I52: 1
A54: FECHA | B54: ABONO | C54: FECHA | D54: ABONO | E54: FECHA | F54: ABONO | G54: FECHA | H54: ABONO
A55: 46083 | B55: 185000 | C55: 46090 | D55: 185000 | E55: 46097 | F55: 185000 | G55: 46104 | H55: 185000 | I55: =B61+D61+F61+H61 -> 740000
A56: 46084 | C56: 46091 | E56: 46098 | G56: 46105
A57: 46085 | C57: 46092 | E57: 46099 | G57: 46106
A58: 46086 | C58: 46093 | E58: 46100 | G58: 46107
A59: 46087 | C59: 46094 | E59: 46101 | G59: 46108
A60: 46088 | C60: 46095 | E60: 46102 | G60: 46109
B61: =SUM(B55:B60) -> 185000 | D61: =SUM(D55:D60) -> 185000 | F61: =SUM(F55:F60) -> 185000 | H61: =SUM(H55:H60) -> 185000 | I61: 5
A62: REF. | C62: REF. | E62: REF. | G62: REF. | I62: 1
A64: FECHA | B64: ABONO | C64: FECHA | D64: ABONO | E64: FECHA | F64: ABONO | G64: FECHA | H64: ABONO
A65: 46111 | B65: 154000 | C65: 46118 | D65: 185000 | E65: 46125 | F65: 185000 | G65: 46132 | H65: 185000 | I65: =B71+D71+F71+H71 -> 709000
A66: 46112 | C66: 46119 | E66: 46126 | G66: 46133
A67: 46113 | C67: 46120 | E67: 46127 | G67: 46134
A68: 46114 | C68: 46121 | E68: 46128 | G68: 46135
A69: 46115 | C69: 46122 | E69: 46129 | G69: 46136
A70: 46116 | C70: 46123 | E70: 46130 | G70: 46137
B71: =SUM(B65:B70) -> 154000 | D71: =SUM(D65:D70) -> 185000 | F71: =SUM(F65:F70) -> 185000 | H71: =SUM(H65:H70) -> 185000 | I71: 6
A72: REF. | C72: REF. | E72: REF. | G72: REF. | I72: 1
A74: FECHA | B74: ABONO | C74: FECHA | D74: ABONO | E74: FECHA | F74: ABONO | G74: FECHA | H74: ABONO
A75: 46139 | B75: 185000 | C75: 46146 | D75: 185000 | E75: 46153 | F75: 185000 | G75: 46160 | H75: 185000 | I75: =B81+D81+F81+H81 -> 740000
A76: 46140 | C76: 46147 | E76: 46154 | G76: 46161
A77: 46141 | C77: 46148 | E77: 46155 | G77: 46162
A78: 46142 | C78: 46149 | E78: 46156 | G78: 46163
A79: 46143 | C79: 46150 | E79: 46157 | G79: 46164
A80: 46144 | C80: 46151 | E80: 46158 | G80: 46165
B81: =SUM(B75:B80) -> 185000 | D81: =SUM(D75:D80) -> 185000 | F81: =SUM(F75:F80) -> 185000 | H81: =SUM(H75:H80) -> 185000 | I81: 7
A82: REF. | C82: REF. | E82: REF. | G82: REF. | I82: 1
A84: FECHA | B84: ABONO | C84: FECHA | D84: ABONO | E84: FECHA | F84: ABONO | G84: FECHA | H84: ABONO
A85: 46167 | C85: 46174 | E85: 46181 | G85: 46188 | I85: =B91+D91+F91+H91 -> 0
A86: 46168 | C86: 46175 | E86: 46182 | G86: 46189
A87: 46169 | C87: 46176 | E87: 46183 | G87: 46190
A88: 46170 | C88: 46177 | E88: 46184 | G88: 46191
A89: 46171 | C89: 46178 | E89: 46185 | G89: 46192
A90: 46172 | C90: 46179 | E90: 46186 | G90: 46193
B91: =B85+B86+B87+B88+B89+B90 -> 0 | D91: =D85+D86+D87+D88+D89+D90 -> 0 | F91: =F85+F86+F87+F88+F89+F90 -> 0 | H91: =H85+H86+H87+H88+H89+H90 -> 0 | I91: 8

Sheet Hoja 2
A1: RENTAL MOTORS S.A.S Nit. 901843215-2
A5: FOTO | C5: =DATA!B4 -> #REF! | D5: =DATA!C4 -> #REF! | E5: =DATA!D4 -> #REF!
C6: =DATA!B5 -> #REF! | D6: =DATA!C5 -> #REF! | E6: =DATA!D5 -> #REF!
C7: =DATA!A5 -> #REF!
C9: =PAGOS!A9 -> #REF! | D9: =PAGOS!C9 -> #REF!
C12: =PAGOS!A10 -> #REF! | D12: =PAGOS!C10 -> #REF!
A13: CUOTAS TOTALES | C13: =PAGOS!H9 -> #REF! | D13: CUOTAS RESTANTES
A14: =PAGOS!D5 -> #REF! | C14: =PAGOS!H11 -> #REF! | D14: =PAGOS!D5-PAGOS!H11 -> #REF!
A15: CODIGO | B15: MOTO | C15: MODELO | D15: MARCA | E15: PLACA
A16: A2175 | B16: PULSAR N160 | C16: 2026 | D16: BAJAJ | E16: RLI49H
C17: SOAT | D17: Traspaso de propiedad | E17: PRESTAMO.
C18: ACTIVO | D18: ACTIVO | E18: 0
