Workbook

Sheet PAGOS
A1: CODIGO | B1: MOTO | C1: MODELO | D1: MARCA | E1: PLACA | F1: MOVIL | G1: PRECIO | H1: INICIAL
A2: A2175 | B2: BOXER | C2: 2025 | D2: BAJAJ | E2: EXI78H | F2: MOVIL 18 | G2: 6800000 | H2: 800000
A4: COSTO -INICIAL | B4: INTERES | C4: COSTO NETO | D4: MESES | E4: MESUAL | F4: QUINCENAL | G4: SEMANAL | H4: DIARIO
A5: =G2-H2 -> 6000000 | B5: =A5*1.69 -> 10140000 | C5: =A5+B5 -> 16140000 | D5: 24 | E5: =C5/D5 -> 672500 | F5: =E5/2 -> 336250 | G5: =F5/2 -> 168125 | H5: =G5/6 -> 28020.833
A6: NOMBRES | B6: APELLIDO | C6: CEDULA | D6: NACIONALIDAD | E6: NUMERO | F6: SOAT | G6: Traspaso de propiedad | H6: DEUDA DE SEMANA
A7: DAIRO TORRES SALCEDO | C7: 9204960 | D7: COLOMBIANA | F7: 0 | G7: 280000 | H7: 201000
H8: MESES
A9: SALDO ACTUAL PAGADO | C9: DEUDA A PAGAR | E9: DEUDA TOTAL. | G9: DEUDA ADQUIRIDA
A10: =I14+I24+I34+I44+I54+I64+I74+I84+I94+I103+I113+I122+I131+I140+I149+I158+I167+I176+I185+I194+I203+I212 -> 14111000 | C10: =C5-A10 -> 2029000 | E10: =C10+G10+G7 -> 2510000 | G10: =H7 -> 201000 | H10: =I21+I31+I41+I51+I61+I71+I81+I91+I101+I110+I120+I129+I138+I147+I156+I165+I174+I183+I192+I201+I210+I219+I228 -> 21
A12: RENTAL MOTORS S.A.S
A13: FECHA | B13: ABONO | C13: FECHA | D13: ABONO | E13: FECHA | F13: ABONO | G13: FECHA | H13: ABONO
C14: 45558 | E14: 45565 | G14: 45572 | I14: =B20+D20+F20+H20 -> 560000
C15: 45559 | E15: 45566 | G15: 45573
C16: 45560 | D16: 168000 | E16: 45567 | F16: 168000 | G16: 45574 | H16: 168000
C17: 45561 | E17: 45568 | G17: 45575
A18: 45555 | B18: 28000 | C18: 45562 | E18: 45569 | G18: 45576
A19: 45556 | B19: 28000 | C19: 45563 | E19: 45570 | G19: 45577
B20: =SUM(B14:B19) -> 56000 | D20: =SUM(D14:D19) -> 168000 | F20: =SUM(F14:F19) -> 168000 | H20: =SUM(H14:H19) -> 168000 | I20: 1
A21: REF. | C21: REF. | E21: REF. | G21: REF. | I21: 1
A23: FECHA | B23: ABONO | C23: FECHA | D23: ABONO | E23: FECHA | F23: ABONO | G23: FECHA | H23: ABONO
A24: 45579 | B24: 168000 | C24: 45586 | D24: 168000 | E24: 45593 | F24: 168000 | G24: 45600 | H24: 168000 | I24: =B30+D30+F30+H30 -> 672000
A25: 45580 | C25: 45587 | E25: 45594 | G25: 45601
A26: 45581 | C26: 45588 | E26: 45595 | G26: 45602
A27: 45582 | C27: 45589 | E27: 45596 | G27: 45603
A28: 45583 | C28: 45590 | E28: 45597 | G28: 45604
A29: 45584 | C29: 45591 | E29: 45598 | G29: 45605
B30: =SUM(B24:B29) -> 168000 | D30: =SUM(D24:D29) -> 168000 | F30: =SUM(F24:F29) -> 168000 | H30: =SUM(H24:H29) -> 168000 | I30: 2
A31: REF. | C31: REF. | E31: REF. | G31: REF. | I31: 1
A33: FECHA | B33: ABONO | C33: FECHA | D33: ABONO | E33: FECHA | F33: ABONO | G33: FECHA | H33: ABONO
A34: 45607 | B34: 168000 | C34: 45614 | D34: 168000 | E34: 45621 | F34: 168000 | G34: 45628 | H34: 168000 | I34: =B40+D40+F40+H40 -> 672000
A35: 45608 | C35: 45615 | E35: 45622 | G35: 45629
A36: 45609 | C36: 45616 | E36: 45623 | G36: 45630
A37: 45610 | C37: 45617 | E37: 45624 | G37: 45631
A38: 45611 | C38: 45618 | E38: 45625 | G38: 45632
A39: 45612 | C39: 45619 | E39: 45626 | G39: 45633
B40: =SUM(B34:B39) -> 168000 | D40: =SUM(D34:D39) -> 168000 | F40: =SUM(F34:F39) -> 168000 | H40: =SUM(H34:H39) -> 168000 | I40: 3
A41: REF. | C41: REF. | E41: REF. | G41: REF. | I41: 1
A43: FECHA | B43: ABONO | C43: FECHA | D43: ABONO | E43: FECHA | F43: ABONO | G43: FECHA | H43: ABONO
A44: 45635 | B44: 168000 | C44: 45642 | D44: 168000 | E44: 45649 | F44: 168000 | G44: 45656 | H44: 168000 | I44: =B50+D50+F50+H50 -> 672000
A45: 45636 | C45: 45643 | E45: 45650 | G45: 45657
A46: 45637 | C46: 45644 | E46: 45651 | G46: 45658
A47: 45638 | C47: 45645 | E47: 45652 | G47: 45659
A48: 45639 | C48: 45646 | E48: 45653 | G48: 45660
A49: 45640 | C49: 45647 | E49: 45654 | G49: 45661
B50: =SUM(B44:B49) -> 168000 | D50: =SUM(D44:D49) -> 168000 | F50: =SUM(F44:F49) -> 168000 | H50: =SUM(H44:H49) -> 168000 | I50: 4
A51: REF. | C51: REF. | E51: REF. | G51: REF. | I51: 1
A53: FECHA | B53: ABONO | C53: FECHA | D53: ABONO | E53: FECHA | F53: ABONO | G53: FECHA | H53: ABONO
A54: 45663 | B54: 112000 | C54: 45670 | D54: 168000 | E54: 45677 | F54: 168000 | G54: 45684 | H54: 168000 | I54: =B60+D60+F60+H60 -> 616000
A55: 45664 | C55: 45671 | E55: 45678 | G55: 45685
A56: 45665 | C56: 45672 | E56: 45679 | G56: 45686
A57: 45666 | C57: 45673 | E57: 45680 | G57: 45687
A58: 45667 | C58: 45674 | E58: 45681 | G58: 45688
A59: 45668 | C59: 45675 | E59: 45682 | G59: 45689
B60: =SUM(B54:B59) -> 112000 | D60: =SUM(D54:D59) -> 168000 | F60: =SUM(F54:F59) -> 168000 | H60: =SUM(H54:H59) -> 168000 | I60: 5
A61: REF. | C61: REF. | E61: REF. | G61: REF. | I61: 1
A63: FECHA | B63: ABONO | C63: FECHA | D63: ABONO | E63: FECHA | F63: ABONO | G63: FECHA | H63: ABONO
A64: 45691 | B64: 168000 | C64: 45698 | D64: 168000 | E64: 45705 | F64: 168000 | G64: 45712 | H64: 168000 | I64: =B70+D70+F70+H70 -> 672000
A65: 45692 | C65: 45699 | E65: 45706 | G65: 45713
A66: 45693 | C66: 45700 | E66: 45707 | G66: 45714
A67: 45694 | C67: 45701 | E67: 45708 | G67: 45715
A68: 45695 | C68: 45702 | E68: 45709 | G68: 45716
A69: 45696 | C69: 45703 | E69: 45710 | G69: 45717
B70: =SUM(B64:B69) -> 168000 | D70: =SUM(D64:D69) -> 168000 | F70: =SUM(F64:F69) -> 168000 | H70: =SUM(H64:H69) -> 168000 | I70: 6
A71: REF. | C71: REF. | E71: REF. | G71: REF. | I71: 1
A73: FECHA | B73: ABONO | C73: FECHA | D73: ABONO | E73: FECHA | F73: ABONO | G73: FECHA | H73: ABONO
A74: 45719 | B74: 168000 | C74: 45726 | D74: 168000 | E74: 45733 | F74: 168000 | G74: 45740 | H74: 168000 | I74: =B80+D80+F80+H80 -> 672000
A75: 45720 | C75: 45727 | E75: 45734 | G75: 45741
A76: 45721 | C76: 45728 | E76: 45735 | G76: 45742
A77: 45722 | C77: 45729 | E77: 45736 | G77: 45743
A78: 45723 | C78: 45730 | E78: 45737 | G78: 45744
A79: 45724 | C79: 45731 | E79: 45738 | G79: 45745
B80: =SUM(B74:B79) -> 168000 | D80: =SUM(D74:D79) -> 168000 | F80: =SUM(F74:F79) -> 168000 | H80: =SUM(H74:H79) -> 168000 | I80: 7
A81: REF. | C81: REF. | E81: REF. | G81: REF. | I81: 1
A83: FECHA | B83: ABONO | C83: FECHA | D83: ABONO | E83: FECHA | F83: ABONO | G83: FECHA | H83: ABONO
A84: 45747 | B84: 168000 | C84: 45754 | D84: 168000 | E84: 45761 | F84: 168000 | G84: 45768 | H84: 168000 | I84: =B90+D90+F90+H90 -> 672000
A85: 45748 | C85: 45755 | E85: 45762 | G85: 45769
A86: 45749 | C86: 45756 | E86: 45763 | G86: 45770
A87: 45750 | C87: 45757 | E87: 45764 | G87: 45771
A88: 45751 | C88: 45758 | E88: 45765 | G88: 45772
A89: 45752 | C89: 45759 | E89: 45766 | G89: 45773
B90: =SUM(B84:B89) -> 168000 | D90: =SUM(D84:D89) -> 168000 | F90: =SUM(F84:F89) -> 168000 | H90: =SUM(H84:H89) -> 168000 | I90: 8
A91: REF. | C91: REF. | E91: REF. | G91: REF. | I91: 1
A93: FECHA | B93: ABONO | C93: FECHA | D93: ABONO | E93: FECHA | F93: ABONO | G93: FECHA | H93: ABONO
A94: 45775 | C94: 45782 | E94: 45789 | G94: 45796 | I94: =B100+D100+F100+H100 -> 672000
A95: 45776 | C95: 45783 | E95: 45790 | G95: 45797
A96: 45777 | B96: 168000 | C96: 45784 | D96: 168000 | E96: 45791 | F96: 168000 | G96: 45798 | H96: 168000
A97: 45778 | C97: 45785 | E97: 45792 | G97: 45799
A98: 45779 | C98: 45786 | E98: 45793 | G98: 45800
A99: 45780 | C99: 45787 | E99: 45794 | G99: 45801
B100: =B96 -> 168000 | D100: =D96 -> 168000 | F100: =F96 -> 168000 | H100: =H96 -> 168000 | I100: 9
I101: 1
A102: FECHA | B102: ABONO | C102: FECHA | D102: ABONO | E102: FECHA | F102: ABONO | G102: FECHA | H102: ABONO
A103: 45803 | B103: 168000 | C103: 45810 | D103: 168000 | E103: 45817 | F103: 168000 | G103: 45824 | H103: 168000 | I103: =B109+D109+F109+H109 -> 672000
A104: 45804 | C104: 45811 | E104: 45818 | G104: 45825
A105: 45805 | C105: 45812 | E105: 45819 | G105: 45826
A106: 45806 | C106: 45813 | E106: 45820 | G106: 45827
A107: 45807 | C107: 45814 | E107: 45821 | G107: 45828
A108: 45808 | C108: 45815 | E108: 45822 | G108: 45829
B109: 168000 | D109: 168000 | F109: =SUM(F103:F108) -> 168000 | H109: =H103 -> 168000 | I109: 10
A110: REF. | C110: REF. | E110: REF. | G110: REF. | I110: 1
...

Sheet SEMANAL
A1: RENTAL MOTORS S.A.S
A3: SOLO PAGOS POR BANCOLOMBIA | C3: =PAGOS!A7 -> DAIRO TORRES SALCEDO
A4: FECHA DEL PRESTAMOS | B4: =PAGOS!A18 -> 45555
A5: COSTO DEL VEICULO | B5: =PAGOS!G2 -> 6800000 | C5: =PAGOS!F2 -> MOVIL 18
A6: INICIAL DEL VEICULO | B6: =PAGOS!H2 -> 800000
A7: PRESTAMO | B7: =PAGOS!A5 -> 6000000
A8: TASA DE INTERES ( 1,7) | B8: =PAGOS!B5 -> 10140000
A9: COSTO NETO DE LA MOTO | B9: =PAGOS!C5 -> 16140000
A10: SOAT | B10: =PAGOS!F7 -> 0 | C10: =PAGOS!G4 -> SEMANAL
A11: PRESTAMO.
A12: Traspaso de propiedad | B12: =PAGOS!G7 -> 280000
A13: MENSUALIDA GPS | B13: 25000 | C13: =PAGOS!G5 -> 168125
A14: TOTAL APAGAR GPS | B14: =B13*B15 -> 600000
A15: MESES A PAGAR | B15: =PAGOS!D5 -> 24
A16: COSTO NETO DE LA MOTO CON LOS TRAMITES Y SERVICIO | B16: =PAGOS!C5 -> 16140000
A17: SALDO PAGADO | B17: SALDO PENDIENTE | C17: DEUDA ADQUIRIDA | D17: MESES ADQUIRIDO | E17: MESES PAGADO
A18: =PAGOS!A10 -> 14111000 | B18: =PAGOS!E10 -> 2510000 | C18: =PAGOS!G10 -> 201000
