Workbook

Sheet PAGOS
A1: CODIGO | B1: MOTO | C1: MODELO | D1: MARCA | E1: PLACA | F1: MOVIL | G1: PRECIO | H1: INICIAL
A2: A219782G | B2: BOXER | C2: 2026 | D2: BAJA | E2: RMF-89H | F2: 11 | G2: 6800000 | H2: 800000
A4: COSTO -INICIAL | B4: INTERES | C4: COSTO NETO | D4: MESES | E4: MESUAL | F4: QUINCENAL | G4: SEMANAL | H4: DIARIO
A5: =G2-H2 -> 6000000 | B5: =A5*170% -> 10200000 | C5: =A5+B5 -> 16200000 | D5: 18 | E5: =C5/D5 -> 900000 | F5: =E5/2 -> 450000 | G5: =F5/2 -> 225000 | H5: =G5/6 -> 37500
A6: NOMBRES | B6: APELLIDO | C6: CEDULA | D6: NACIONALIDAD | E6: NUMERO | F6: SOAT | G6: Traspaso de propiedad | H6: DEUDA DE SEMANA
A7: YOBANI ANDRES GARZON MARTINEZ | C7: 1002249081 | D7: COLOMBIANO | E7: 3147591450 | F7: 380000 | G7: 280000
H8: MESES
A9: SALDO ACTUAL PAGADO | C9: DEUDA A PAGAR | E9: DEUDA TOTAL. | G9: DEUDA ADQUIRIDA
A10: =I14+I24+I34+I44+I54+I64+I74+I84+I94+I104+I114 -> 9159000 | C10: =C5-A10 -> 7041000 | H10: =I21+I31+I41+I51+I61+I71+I81+I91+I101+I111 -> 10
A12: RENTAL MOTORS S.A.S
A13: FECHA | B13: ABONO | C13: FECHA | D13: ABONO | E13: FECHA | F13: ABONO | G13: FECHA | H13: ABONO
C14: 45901 | E14: 45908 | G14: 45915 | I14: =B20+D20+F20+H20 -> 889000
C15: 45902 | E15: 45909 | G15: 45916
A16: 45896 | B16: 180000 | C16: 45903 | D16: 260000 | E16: 45910 | F16: 224500 | G16: 45917 | H16: 224500
A17: 45897 | C17: 45904 | E17: 45911 | G17: 45918
A18: 45898 | C18: 45905 | E18: 45912 | G18: 45919
A19: 45899 | C19: 45906 | E19: 45913 | G19: 45920
B20: =SUM(B14:B19) -> 180000 | D20: =SUM(D14:D19) -> 260000 | F20: =SUM(F14:F19) -> 224500 | H20: =SUM(H14:H19) -> 224500 | I20: 1
A21: REF. | C21: REF. | E21: REF. | G21: REF. | I21: 1
A23: FECHA | B23: ABONO | C23: FECHA | D23: ABONO | E23: FECHA | F23: ABONO | G23: FECHA | H23: ABONO
A24: 45922 | C24: 45929 | E24: 45936 | G24: 45943 | I24: =B30+D30+F30+H30 -> 898000
A25: 45923 | C25: 45930 | E25: 45937 | G25: 45944
A26: 45924 | B26: 224500 | C26: 45931 | D26: 224500 | E26: 45938 | F26: 224500 | G26: 45945 | H26: 224500
A27: 45925 | C27: 45932 | E27: 45939 | G27: 45946
A28: 45926 | C28: 45933 | E28: 45940 | G28: 45947
A29: 45927 | C29: 45934 | E29: 45941 | G29: 45948
B30: =SUM(B24:B29) -> 224500 | D30: =SUM(D24:D29) -> 224500 | F30: =SUM(F24:F29) -> 224500 | H30: =SUM(H24:H29) -> 224500 | I30: 2
A31: REF. | C31: REF. | E31: REF. | G31: REF. | I31: 1
A33: FECHA | B33: ABONO | C33: FECHA | D33: ABONO | E33: FECHA | F33: ABONO | G33: FECHA | H33: ABONO
A34: 45950 | C34: 45957 | E34: 45964 | G34: 45971 | I34: =B40+D40+F40+H40 -> 897500
A35: 45951 | C35: 45958 | E35: 45965 | G35: 45972
A36: 45952 | B36: 224500 | C36: 45959 | D36: 224500 | E36: 45966 | F36: 224500 | G36: 45973 | H36: 224000
A37: 45953 | C37: 45960 | E37: 45967 | G37: 45974
A38: 45954 | C38: 45961 | E38: 45968 | G38: 45975
A39: 45955 | C39: 45962 | E39: 45969 | G39: 45976
B40: =SUM(B34:B39) -> 224500 | D40: =SUM(D34:D39) -> 224500 | F40: =SUM(F34:F39) -> 224500 | H40: =SUM(H34:H39) -> 224000 | I40: 3
A41: REF. | C41: REF. | E41: REF. | G41: REF. | I41: 1
A43: FECHA | B43: ABONO | C43: FECHA | D43: ABONO | E43: FECHA | F43: ABONO | G43: FECHA | H43: ABONO
A44: 45978 | B44: 224500 | C44: 45985 | D44: 224500 | E44: 45992 | F44: 224500 | G44: 45999 | H44: 224500 | I44: =B50+D50+F50+H50 -> 898000
A45: 45979 | C45: 45986 | E45: 45993 | G45: 46000
A46: 45980 | C46: 45987 | E46: 45994 | G46: 46001
A47: 45981 | C47: 45988 | E47: 45995 | G47: 46002
A48: 45982 | C48: 45989 | E48: 45996 | G48: 46003
A49: 45983 | C49: 45990 | E49: 45997 | G49: 46004
B50: =B44 -> 224500 | D50: =D44 -> 224500 | F50: =F44 -> 224500 | H50: =H44 -> 224500 | I50: 4
A51: REF. | C51: REF. | E51: REF. | G51: REF. | I51: 1
A53: FECHA | B53: ABONO | C53: FECHA | D53: ABONO | E53: FECHA | F53: ABONO | G53: FECHA | H53: ABONO
A54: 46006 | B54: 224500 | C54: 46013 | E54: 46020 | G54: 46027 | I54: =B60+D60+F60+H60 -> 898000
A55: 46007 | C55: 46014 | E55: 46021 | G55: 46028
A56: 46008 | C56: 46015 | D56: 224500 | E56: 46022 | F56: 224500 | G56: 46029 | H56: 224500
A57: 46009 | C57: 46016 | E57: 46023 | G57: 46030
A58: 46010 | C58: 46017 | E58: 46024 | G58: 46031
A59: 46011 | C59: 46018 | E59: 46025 | G59: 46032
B60: =SUM(B54:B59) -> 224500 | D60: =SUM(D54:D59) -> 224500 | F60: =SUM(F54:F59) -> 224500 | H60: =SUM(H54:H59) -> 224500 | I60: 5
A61: REF. | C61: REF. | E61: REF. | G61: REF. | I61: 1
A63: FECHA | B63: ABONO | C63: FECHA | D63: ABONO | E63: FECHA | F63: ABONO | G63: FECHA | H63: ABONO
A64: 46034 | C64: 46041 | E64: 46048 | G64: 46055 | I64: =B70+D70+F70+H70 -> 898000
A65: 46035 | C65: 46042 | E65: 46049 | G65: 46056
A66: 46036 | B66: 224500 | C66: 46043 | D66: 224500 | E66: 46050 | F66: 224500 | G66: 46057 | H66: 224500
A67: 46037 | C67: 46044 | E67: 46051 | G67: 46058
A68: 46038 | C68: 46045 | E68: 46052 | G68: 46059
A69: 46039 | C69: 46046 | E69: 46053 | G69: 46060
B70: =SUM(B64:B69) -> 224500 | D70: =SUM(D64:D69) -> 224500 | F70: =SUM(F64:F69) -> 224500 | H70: =SUM(H64:H69) -> 224500 | I70: 6
A71: REF. | B71: M05284498 | C71: REF. | E71: REF. | G71: REF. | I71: 1
A73: FECHA | B73: ABONO | C73: FECHA | D73: ABONO | E73: FECHA | F73: ABONO | G73: FECHA | H73: ABONO
A74: 46062 | C74: 46069 | E74: 46076 | G74: 46083 | I74: =B80+D80+F80+H80 -> 896500
A75: 46063 | C75: 46070 | E75: 46077 | G75: 46084
A76: 46064 | B76: 224500 | C76: 46071 | D76: 224000 | E76: 46078 | F76: 224000 | G76: 46085 | H76: 224000
A77: 46065 | C77: 46072 | E77: 46079 | G77: 46086
A78: 46066 | C78: 46073 | E78: 46080 | G78: 46087
A79: 46067 | C79: 46074 | E79: 46081 | G79: 46088
B80: =SUM(B74:B79) -> 224500 | D80: =SUM(D74:D79) -> 224000 | F80: =SUM(F74:F79) -> 224000 | H80: =SUM(H74:H79) -> 224000 | I80: 7
A81: REF. | C81: REF. | E81: REF. | G81: REF. | I81: 1
A83: FECHA | B83: ABONO | C83: FECHA | D83: ABONO | E83: FECHA | F83: ABONO | G83: FECHA | H83: ABONO
A84: 46090 | C84: 46097 | E84: 46104 | G84: 46111 | I84: =B90+D90+F90+H90 -> 863500
A85: 46091 | B85: 224500 | C85: 46098 | E85: 46105 | G85: 46112
A86: 46092 | C86: 46099 | E86: 46106 | G86: 46113
A87: 46093 | C87: 46100 | D87: 224500 | E87: 46107 | F87: 224500 | G87: 46114 | H87: 190000
A88: 46094 | C88: 46101 | E88: 46108 | G88: 46115
A89: 46095 | C89: 46102 | E89: 46109 | G89: 46116
B90: =SUM(B84:B89) -> 224500 | D90: =SUM(D84:D89) -> 224500 | F90: =SUM(F84:F89) -> 224500 | H90: =SUM(H84:H89) -> 190000 | I90: 8
A91: REF. | C91: REF. | E91: REF. | G91: REF. | I91: 1
A93: FECHA | B93: ABONO | C93: FECHA | D93: ABONO | E93: FECHA | F93: ABONO | G93: FECHA | H93: ABONO
A94: 46118 | B94: 224500 | C94: 46125 | D94: 224500 | E94: 46132 | F94: 224500 | G94: 46125 | H94: 224500 | I94: =B100+D100+F100+H100 -> 898000
A95: 46119 | C95: 46126 | E95: 46133 | G95: 46126
A96: 46120 | C96: 46127 | E96: 46134 | G96: 46127
A97: 46121 | C97: 46128 | E97: 46135 | G97: 46128
A98: 46122 | C98: 46129 | E98: 46136 | G98: 46129
A99: 46123 | C99: 46130 | E99: 46137 | G99: 46130
B100: =SUM(B94:B99) -> 224500 | D100: =SUM(D94:D99) -> 224500 | F100: =SUM(F94:F99) -> 224500 | H100: =SUM(H94:H99) -> 224500 | I100: 9
A101: REF. | C101: REF. | E101: REF. | G101: REF. | I101: 1
A103: FECHA | B103: ABONO | C103: FECHA | D103: ABONO | E103: FECHA | F103: ABONO | G103: FECHA | H103: ABONO
A104: 46132 | B104: 224500 | C104: 46139 | D104: 224500 | E104: 46146 | F104: 224500 | G104: 46153 | H104: 224500 | I104: =B110+D110+F110+H110 -> 898000
A105: 46133 | C105: 46140 | E105: 46147 | G105: 46154
A106: 46134 | C106: 46141 | E106: 46148 | G106: 46155
A107: 46135 | C107: 46142 | E107: 46149 | G107: 46156
A108: 46136 | C108: 46143 | E108: 46150 | G108: 46157
A109: 46137 | C109: 46144 | E109: 46151 | G109: 46158
B110: =SUM(B104:B109) -> 224500 | D110: =SUM(D104:D109) -> 224500 | F110: =SUM(F104:F109) -> 224500 | H110: =SUM(H104:H109) -> 224500 | I110: 10
A111: REF. | C111: REF. | E111: REF. | G111: REF. | I111: 1
...

Sheet SEMANAL
A1: RENTAL MOTORS S.A.S
A3: SOLO PAGOS POR BANCOLOMBIA | C3: =PAGOS!A7 -> YOBANI ANDRES GARZON MARTINEZ
A4: FECHA DEL PRESTAMOS | B4: =PAGOS!A16 -> 45896
A5: COSTO DEL VEICULO | B5: =PAGOS!G2 -> 6800000 | C5: MOVIL 11
A6: INICIAL DEL VEICULO | B6: =PAGOS!H2 -> 800000
A7: PRESTAMO | B7: =PAGOS!A5 -> 6000000
A8: TASA DE INTERES ( 1,7) | B8: =PAGOS!B5 -> 10200000
A9: COSTO NETO DE LA MOTO | B9: =PAGOS!C5 -> 16200000
A10: SOAT | B10: =PAGOS!F7 -> 380000 | C10: =PAGOS!G4 -> SEMANAL
A11: PRESTAMO.
A12: Traspaso de propiedad | B12: =PAGOS!G7 -> 280000
A13: MENSUALIDA GPS | B13: 25000 | C13: =PAGOS!G5 -> 225000
A14: TOTAL APAGAR GPS | B14: =B13*B15 -> 450000
A15: MESES A PAGAR | B15: =PAGOS!D5 -> 18
A16: COSTO NETO DE LA MOTO CON LOS TRAMITES Y SERVICIO | B16: =PAGOS!C5 -> 16200000
A17: SALDO PAGADO | B17: SALDO PENDIENTE | C17: DEUDA ADQUIRIDA | D17: MESES ADQUIRIDO | E17: MESES PAGADO
A18: =PAGOS!A10 -> 9159000 | B18: =PAGOS!C10 -> 7041000
